README.rst
setup.py
ident/__init__.py
ident.egg-info/PKG-INFO
ident.egg-info/SOURCES.txt
ident.egg-info/dependency_links.txt
ident.egg-info/entry_points.txt
ident.egg-info/not-zip-safe
ident.egg-info/requires.txt
ident.egg-info/top_level.txt
ident/commands/__init__.py
ident/commands/verify.py