Metadata-Version: 2.1
Name: ident
Version: 1.0.2
Summary: Identify with challenge messsage and SSH key.
Home-page: https://github.com/mindey/ident
Author: Mindey
Author-email: ~@mindey.com
License: MIT
Platform: UNKNOWN
Provides-Extra: test
